combatlearn/__init__.py
combatlearn/combat.py
combatlearn-1.1.2.dist-info/licenses/LICENSE
combatlearn-1.1.2.dist-info/METADATA
combatlearn-1.1.2.dist-info/WHEEL
combatlearn-1.1.2.dist-info/top_level.txt
combatlearn-1.1.2.dist-info/RECORD
