Metadata-Version: 2.4
Name: combatlearn
Version: 1.1.2
Summary: Batch-effect harmonization for machine learning frameworks.
Author-email: Ettore Rocchi <ettoreroc@gmail.com>
License: MIT
Keywords: machine-learning,harmonization,combat,preprocessing
Classifier: Development Status :: 3 - Alpha
Classifier: Intended Audience :: Science/Research
Classifier: Operating System :: OS Independent
Classifier: Programming Language :: Python :: 3
Requires-Python: >=3.10
License-File: LICENSE
Requires-Dist: pandas>=1.3
Requires-Dist: numpy>=1.21
Requires-Dist: scikit-learn>=1.2
Requires-Dist: matplotlib>=3.4
Requires-Dist: plotly>=5.0
Requires-Dist: nbformat>=4.2
Requires-Dist: umap-learn>=0.5
Provides-Extra: dev
Requires-Dist: pytest>=7; extra == "dev"
Requires-Dist: ruff>=0.8; extra == "dev"
Requires-Dist: pre-commit>=3.0; extra == "dev"
Provides-Extra: docs
Requires-Dist: sphinx>=7.0.0; extra == "docs"
Requires-Dist: pydata-sphinx-theme>=0.15.0; extra == "docs"
Requires-Dist: myst-parser>=3.0.0; extra == "docs"
Requires-Dist: sphinx-copybutton>=0.5.0; extra == "docs"
Requires-Dist: linkify-it-py>=2.0.0; extra == "docs"
Dynamic: license-file
